{
	"configurations" : 
	[
		{
			"directories" : 
			[
				{
					"build" : ".",
					"childIndexes" : 
					[
						1
					],
					"jsonFile" : "directory-.-Debug-d0094a50bb2071803777.json",
					"minimumCMakeVersion" : 
					{
						"string" : "3.0.0"
					},
					"projectIndex" : 0,
					"source" : ".",
					"targetIndexes" : 
					[
						0,
						1
					]
				},
				{
					"build" : "src",
					"jsonFile" : "directory-src-Debug-c94b7c2814d5a21df52c.json",
					"minimumCMakeVersion" : 
					{
						"string" : "3.0.0"
					},
					"parentIndex" : 0,
					"projectIndex" : 0,
					"source" : "src",
					"targetIndexes" : 
					[
						2
					]
				}
			],
			"name" : "Debug",
			"projects" : 
			[
				{
					"directoryIndexes" : 
					[
						0,
						1
					],
					"name" : "riscv-sim",
					"targetIndexes" : 
					[
						0,
						1,
						2
					]
				}
			],
			"targets" : 
			[
				{
					"directoryIndex" : 0,
					"id" : "ALL_BUILD::@6890427a1f51a3e7e1df",
					"jsonFile" : "target-ALL_BUILD-Debug-b97a8b50b6e19755cae7.json",
					"name" : "ALL_BUILD",
					"projectIndex" : 0
				},
				{
					"directoryIndex" : 0,
					"id" : "ZERO_CHECK::@6890427a1f51a3e7e1df",
					"jsonFile" : "target-ZERO_CHECK-Debug-a6c503b92254080e82ec.json",
					"name" : "ZERO_CHECK",
					"projectIndex" : 0
				},
				{
					"directoryIndex" : 1,
					"id" : "cpu::@145eef247bfb46b6828c",
					"jsonFile" : "target-cpu-Debug-b63ca7b3f79024e3ac0e.json",
					"name" : "cpu",
					"projectIndex" : 0
				}
			]
		},
		{
			"directories" : 
			[
				{
					"build" : ".",
					"childIndexes" : 
					[
						1
					],
					"jsonFile" : "directory-.-Release-d0094a50bb2071803777.json",
					"minimumCMakeVersion" : 
					{
						"string" : "3.0.0"
					},
					"projectIndex" : 0,
					"source" : ".",
					"targetIndexes" : 
					[
						0,
						1
					]
				},
				{
					"build" : "src",
					"jsonFile" : "directory-src-Release-c94b7c2814d5a21df52c.json",
					"minimumCMakeVersion" : 
					{
						"string" : "3.0.0"
					},
					"parentIndex" : 0,
					"projectIndex" : 0,
					"source" : "src",
					"targetIndexes" : 
					[
						2
					]
				}
			],
			"name" : "Release",
			"projects" : 
			[
				{
					"directoryIndexes" : 
					[
						0,
						1
					],
					"name" : "riscv-sim",
					"targetIndexes" : 
					[
						0,
						1,
						2
					]
				}
			],
			"targets" : 
			[
				{
					"directoryIndex" : 0,
					"id" : "ALL_BUILD::@6890427a1f51a3e7e1df",
					"jsonFile" : "target-ALL_BUILD-Release-b97a8b50b6e19755cae7.json",
					"name" : "ALL_BUILD",
					"projectIndex" : 0
				},
				{
					"directoryIndex" : 0,
					"id" : "ZERO_CHECK::@6890427a1f51a3e7e1df",
					"jsonFile" : "target-ZERO_CHECK-Release-a6c503b92254080e82ec.json",
					"name" : "ZERO_CHECK",
					"projectIndex" : 0
				},
				{
					"directoryIndex" : 1,
					"id" : "cpu::@145eef247bfb46b6828c",
					"jsonFile" : "target-cpu-Release-173077d69fd66da092a4.json",
					"name" : "cpu",
					"projectIndex" : 0
				}
			]
		},
		{
			"directories" : 
			[
				{
					"build" : ".",
					"childIndexes" : 
					[
						1
					],
					"jsonFile" : "directory-.-MinSizeRel-d0094a50bb2071803777.json",
					"minimumCMakeVersion" : 
					{
						"string" : "3.0.0"
					},
					"projectIndex" : 0,
					"source" : ".",
					"targetIndexes" : 
					[
						0,
						1
					]
				},
				{
					"build" : "src",
					"jsonFile" : "directory-src-MinSizeRel-c94b7c2814d5a21df52c.json",
					"minimumCMakeVersion" : 
					{
						"string" : "3.0.0"
					},
					"parentIndex" : 0,
					"projectIndex" : 0,
					"source" : "src",
					"targetIndexes" : 
					[
						2
					]
				}
			],
			"name" : "MinSizeRel",
			"projects" : 
			[
				{
					"directoryIndexes" : 
					[
						0,
						1
					],
					"name" : "riscv-sim",
					"targetIndexes" : 
					[
						0,
						1,
						2
					]
				}
			],
			"targets" : 
			[
				{
					"directoryIndex" : 0,
					"id" : "ALL_BUILD::@6890427a1f51a3e7e1df",
					"jsonFile" : "target-ALL_BUILD-MinSizeRel-b97a8b50b6e19755cae7.json",
					"name" : "ALL_BUILD",
					"projectIndex" : 0
				},
				{
					"directoryIndex" : 0,
					"id" : "ZERO_CHECK::@6890427a1f51a3e7e1df",
					"jsonFile" : "target-ZERO_CHECK-MinSizeRel-a6c503b92254080e82ec.json",
					"name" : "ZERO_CHECK",
					"projectIndex" : 0
				},
				{
					"directoryIndex" : 1,
					"id" : "cpu::@145eef247bfb46b6828c",
					"jsonFile" : "target-cpu-MinSizeRel-5046544f046fb69ca8fc.json",
					"name" : "cpu",
					"projectIndex" : 0
				}
			]
		},
		{
			"directories" : 
			[
				{
					"build" : ".",
					"childIndexes" : 
					[
						1
					],
					"jsonFile" : "directory-.-RelWithDebInfo-d0094a50bb2071803777.json",
					"minimumCMakeVersion" : 
					{
						"string" : "3.0.0"
					},
					"projectIndex" : 0,
					"source" : ".",
					"targetIndexes" : 
					[
						0,
						1
					]
				},
				{
					"build" : "src",
					"jsonFile" : "directory-src-RelWithDebInfo-c94b7c2814d5a21df52c.json",
					"minimumCMakeVersion" : 
					{
						"string" : "3.0.0"
					},
					"parentIndex" : 0,
					"projectIndex" : 0,
					"source" : "src",
					"targetIndexes" : 
					[
						2
					]
				}
			],
			"name" : "RelWithDebInfo",
			"projects" : 
			[
				{
					"directoryIndexes" : 
					[
						0,
						1
					],
					"name" : "riscv-sim",
					"targetIndexes" : 
					[
						0,
						1,
						2
					]
				}
			],
			"targets" : 
			[
				{
					"directoryIndex" : 0,
					"id" : "ALL_BUILD::@6890427a1f51a3e7e1df",
					"jsonFile" : "target-ALL_BUILD-RelWithDebInfo-b97a8b50b6e19755cae7.json",
					"name" : "ALL_BUILD",
					"projectIndex" : 0
				},
				{
					"directoryIndex" : 0,
					"id" : "ZERO_CHECK::@6890427a1f51a3e7e1df",
					"jsonFile" : "target-ZERO_CHECK-RelWithDebInfo-a6c503b92254080e82ec.json",
					"name" : "ZERO_CHECK",
					"projectIndex" : 0
				},
				{
					"directoryIndex" : 1,
					"id" : "cpu::@145eef247bfb46b6828c",
					"jsonFile" : "target-cpu-RelWithDebInfo-e569a5404db8694fd3e8.json",
					"name" : "cpu",
					"projectIndex" : 0
				}
			]
		}
	],
	"kind" : "codemodel",
	"paths" : 
	{
		"build" : "C:/Users/patrick/Projects/riscv-sim/build",
		"source" : "C:/Users/patrick/Projects/riscv-sim"
	},
	"version" : 
	{
		"major" : 2,
		"minor" : 4
	}
}
